chemcrow/__init__.py
chemcrow/utils.py
chemcrow/version.py
chemcrow/agents/__init__.py
chemcrow/agents/chemcrow.py
chemcrow/agents/prompts.py
chemcrow/agents/tools.py
chemcrow/data/chem_wep_smi.csv
chemcrow/frontend/__init__.py
chemcrow/frontend/streamlit_callback_handler.py
chemcrow/frontend/utils.py
chemcrow/tools/__init__.py
chemcrow/tools/chemspace.py
chemcrow/tools/converters.py
chemcrow/tools/prompts.py
chemcrow/tools/rdkit.py
chemcrow/tools/rxn4chem.py
chemcrow/tools/safety.py
chemcrow/tools/search.py
chemcrow-0.3.24.dist-info/LICENSE
chemcrow-0.3.24.dist-info/METADATA
chemcrow-0.3.24.dist-info/WHEEL
chemcrow-0.3.24.dist-info/top_level.txt
chemcrow-0.3.24.dist-info/RECORD
