Metadata-Version: 2.1
Name: chemcrow
Version: 0.3.24
Summary: Accurate solution of reasoning-intensive chemical tasks, powered by LLMs.
Home-page: https://github.com/ur-whitelab/chemcrow-public
Author: Andres M Bran, Sam Cox, Andrew White, Philippe Schwaller
Author-email: andrew.white@rochester.edu
License: MIT
Classifier: Programming Language :: Python :: 3.10
Classifier: Programming Language :: Python :: 3.11
Classifier: License :: OSI Approved :: MIT License
Classifier: Operating System :: OS Independent
Requires-Python: >=3.9, <3.12
License-File: LICENSE
Requires-Dist: ipython
Requires-Dist: python-dotenv
Requires-Dist: rdkit
Requires-Dist: synspace
Requires-Dist: openai ==0.27.8
Requires-Dist: molbloom
Requires-Dist: paper-qa ==1.1.1
Requires-Dist: google-search-results
Requires-Dist: langchain <=0.0.275,>=0.0.234
Requires-Dist: langchain-core ==0.0.1
Requires-Dist: nest-asyncio
Requires-Dist: tiktoken
Requires-Dist: rmrkl
Requires-Dist: streamlit
Requires-Dist: rxn4chemistry
Requires-Dist: duckduckgo-search
Requires-Dist: wikipedia
